coilspy/__init__.py
coilspy/coilclass.py
coilspy/generate_complex_sum.py
coilspy/generate_kernel.py
coilspy/initialization.py
coilspy/rescale_funs.py
coilspy/selector.py
coilspy/viz/__init__.py
coilspy/viz/plot_complex_vectors.py
coilspy-0.1.0.dist-info/LICENSE
coilspy-0.1.0.dist-info/METADATA
coilspy-0.1.0.dist-info/WHEEL
coilspy-0.1.0.dist-info/RECORD
