Metadata-Version: 2.1
Name: coilspy
Version: 0.1.0
Summary: A Python package for generating self-referencing Bayesian fields, also known as coils.
License: MIT
Author: ap0phasi
Author-email: 66261738+ap0phasi@users.noreply.github.com
Requires-Python: >=3.12,<4.0
Classifier: License :: OSI Approved :: MIT License
Classifier: Programming Language :: Python :: 3
Classifier: Programming Language :: Python :: 3.12
Requires-Dist: matplotlib (>=3.8.3,<4.0.0)
Requires-Dist: numpy (>=1.26.4,<2.0.0)
Requires-Dist: torch (>=2.2.1,<3.0.0)
